{
  "cells": [
    {
      "name": "K4_N4",
      "K": 4,
      "R": 2,
      "C": 2,
      "chip_rows": 2,
      "chip_cols": 2
    },
    {
      "name": "K4_N8",
      "K": 4,
      "R": 2,
      "C": 2,
      "chip_rows": 2,
      "chip_cols": 4
    },
    {
      "name": "K4_N16",
      "K": 4,
      "R": 2,
      "C": 2,
      "chip_rows": 4,
      "chip_cols": 4
    },
    {
      "name": "K8_N4",
      "K": 8,
      "R": 2,
      "C": 4,
      "chip_rows": 2,
      "chip_cols": 2
    },
    {
      "name": "K8_N8",
      "K": 8,
      "R": 2,
      "C": 4,
      "chip_rows": 2,
      "chip_cols": 4
    },
    {
      "name": "K8_N16",
      "K": 8,
      "R": 2,
      "C": 4,
      "chip_rows": 4,
      "chip_cols": 4
    },
    {
      "name": "K16_N4",
      "K": 16,
      "R": 4,
      "C": 4,
      "chip_rows": 2,
      "chip_cols": 2
    },
    {
      "name": "K16_N8",
      "K": 16,
      "R": 4,
      "C": 4,
      "chip_rows": 2,
      "chip_cols": 4
    },
    {
      "name": "K16_N16",
      "K": 16,
      "R": 4,
      "C": 4,
      "chip_rows": 4,
      "chip_cols": 4
    },
    {
      "name": "K32_N4",
      "K": 32,
      "R": 4,
      "C": 8,
      "chip_rows": 2,
      "chip_cols": 2
    },
    {
      "name": "K32_N8",
      "K": 32,
      "R": 4,
      "C": 8,
      "chip_rows": 2,
      "chip_cols": 4
    },
    {
      "name": "K32_N16",
      "K": 32,
      "R": 4,
      "C": 8,
      "chip_rows": 4,
      "chip_cols": 4
    }
  ],
  "rows": [
    {
      "cell": "K16_N16",
      "wl": "ep_all_to_all",
      "nl": 83.08446525745418,
      "heaviest": [
        0,
        2
      ],
      "lat_mesh_median": 47.9638,
      "lat_p1_median": 47.3889,
      "lat_mesh_all": [
        47.9638,
        48.1066,
        47.7991,
        47.8948,
        48.2173
      ],
      "lat_p1_all": [
        47.325,
        47.4958,
        47.2369,
        47.3889,
        47.5748
      ],
      "probe_gain": 1.1986122867662685
    },
    {
      "cell": "K16_N16",
      "wl": "fsdp",
      "nl": 64.78873239436619,
      "heaviest": [
        0,
        2
      ],
      "lat_mesh_median": 39.3591,
      "lat_p1_median": 39.0348,
      "lat_mesh_all": [
        39.4756,
        39.2936,
        39.2894,
        39.4391,
        39.3591
      ],
      "lat_p1_all": [
        39.097,
        38.9294,
        38.8609,
        39.1162,
        39.0348
      ],
      "probe_gain": 0.8239517671898009
    },
    {
      "cell": "K16_N16",
      "wl": "hybrid_tp_pp",
      "nl": 65.75342465753425,
      "heaviest": [
        7,
        8
      ],
      "lat_mesh_median": 39.3591,
      "lat_p1_median": 198.717,
      "lat_mesh_all": [
        39.4756,
        39.2936,
        39.2894,
        39.4391,
        39.3591
      ],
      "lat_p1_all": [
        232.808,
        256.593,
        189.383,
        198.717,
        167.092
      ],
      "probe_gain": -404.88197138654095
    },
    {
      "cell": "K16_N16",
      "wl": "moe",
      "nl": 79.375,
      "heaviest": [
        0,
        6
      ],
      "lat_mesh_median": 49.1576,
      "lat_p1_median": 47.9945,
      "lat_mesh_all": [
        48.9335,
        49.7406,
        49.6887,
        49.0995,
        49.1576
      ],
      "lat_p1_all": [
        46.8565,
        47.9945,
        48.1217,
        48.0507,
        47.5396
      ],
      "probe_gain": 2.3660634367829187
    },
    {
      "cell": "K16_N16",
      "wl": "ring_allreduce",
      "nl": 25.0,
      "heaviest": [
        0,
        15
      ],
      "lat_mesh_median": 37.6133,
      "lat_p1_median": 34.5385,
      "lat_mesh_all": [
        37.4659,
        37.3638,
        37.6133,
        37.7078,
        37.6953
      ],
      "lat_p1_all": [
        34.5214,
        34.3309,
        34.5385,
        34.6229,
        34.5731
      ],
      "probe_gain": 8.174767967713557
    },
    {
      "cell": "K16_N16",
      "wl": "tree_allreduce",
      "nl": 33.333333333333336,
      "heaviest": [
        0,
        2
      ],
      "lat_mesh_median": 32.9268,
      "lat_p1_median": 32.7025,
      "lat_mesh_all": [
        33.0316,
        32.8445,
        32.8869,
        33.0034,
        32.9268
      ],
      "lat_p1_all": [
        32.8172,
        32.6251,
        32.686,
        32.7784,
        32.7025
      ],
      "probe_gain": 0.6812080129256396
    },
    {
      "cell": "K16_N16",
      "wl": "uniform_random",
      "nl": 79.08450363915355,
      "heaviest": [
        6,
        8
      ],
      "lat_mesh_median": 48.3661,
      "lat_p1_median": 183.333,
      "lat_mesh_all": [
        48.4254,
        48.3661,
        48.2251,
        48.3537,
        48.5634
      ],
      "lat_p1_all": [
        202.737,
        183.298,
        190.332,
        182.437,
        183.333
      ],
      "probe_gain": -279.0526835945011
    },
    {
      "cell": "K16_N4",
      "wl": "ep_all_to_all",
      "nl": 83.08446525745418,
      "heaviest": [
        0,
        2
      ],
      "lat_mesh_median": 37.804,
      "lat_p1_median": 33.8495,
      "lat_mesh_all": [
        37.6012,
        37.804,
        38.1726,
        37.1274,
        37.9283
      ],
      "lat_p1_all": [
        33.9066,
        33.8246,
        33.9421,
        33.5853,
        33.8495
      ],
      "probe_gain": 10.460533276901922
    },
    {
      "cell": "K16_N4",
      "wl": "fsdp",
      "nl": 64.78873239436619,
      "heaviest": [
        0,
        2
      ],
      "lat_mesh_median": 26.9694,
      "lat_p1_median": 26.5386,
      "lat_mesh_all": [
        26.9694,
        27.0098,
        26.9706,
        26.9539,
        26.9338
      ],
      "lat_p1_all": [
        26.5376,
        26.5936,
        26.5386,
        26.5642,
        26.4944
      ],
      "probe_gain": 1.5973659035796177
    },
    {
      "cell": "K16_N4",
      "wl": "hybrid_tp_pp",
      "nl": 65.75342465753425,
      "heaviest": [
        7,
        8
      ],
      "lat_mesh_median": 27.0365,
      "lat_p1_median": 25.832,
      "lat_mesh_all": [
        27.0988,
        27.0298,
        27.1,
        26.9617,
        27.0365
      ],
      "lat_p1_all": [
        25.8573,
        25.7881,
        25.8845,
        25.7393,
        25.832
      ],
      "probe_gain": 4.455088491483733
    },
    {
      "cell": "K16_N4",
      "wl": "moe",
      "nl": 79.375,
      "heaviest": [
        0,
        6
      ],
      "lat_mesh_median": 33.6138,
      "lat_p1_median": 30.5946,
      "lat_mesh_all": [
        33.4764,
        33.5841,
        33.7143,
        33.6138,
        33.6883
      ],
      "lat_p1_all": [
        30.5482,
        30.5758,
        30.6317,
        30.6054,
        30.5946
      ],
      "probe_gain": 8.982025239633716
    },
    {
      "cell": "K16_N4",
      "wl": "ring_allreduce",
      "nl": 25.0,
      "heaviest": [
        0,
        15
      ],
      "lat_mesh_median": 26.0588,
      "lat_p1_median": 24.2181,
      "lat_mesh_all": [
        26.2012,
        25.9656,
        26.165,
        26.0479,
        26.0588
      ],
      "lat_p1_all": [
        24.2181,
        24.0796,
        24.2964,
        24.2699,
        24.1328
      ],
      "probe_gain": 7.063640689517558
    },
    {
      "cell": "K16_N4",
      "wl": "tree_allreduce",
      "nl": 33.333333333333336,
      "heaviest": [
        0,
        2
      ],
      "lat_mesh_median": 22.6731,
      "lat_p1_median": 22.5006,
      "lat_mesh_all": [
        22.7658,
        22.6454,
        22.6176,
        22.6731,
        22.7892
      ],
      "lat_p1_all": [
        22.5837,
        22.4619,
        22.4417,
        22.5006,
        22.6182
      ],
      "probe_gain": 0.7608134749990207
    },
    {
      "cell": "K16_N4",
      "wl": "uniform_random",
      "nl": 79.08450363915355,
      "heaviest": [
        6,
        8
      ],
      "lat_mesh_median": 30.8485,
      "lat_p1_median": 30.123,
      "lat_mesh_all": [
        30.7195,
        30.6563,
        30.8485,
        30.9061,
        30.8938
      ],
      "lat_p1_all": [
        29.9671,
        29.8959,
        30.123,
        30.255,
        30.1687
      ],
      "probe_gain": 2.351816133685593
    },
    {
      "cell": "K16_N8",
      "wl": "ep_all_to_all",
      "nl": 83.08446525745418,
      "heaviest": [
        0,
        2
      ],
      "lat_mesh_median": 415.451,
      "lat_p1_median": 56.7313,
      "lat_mesh_all": [
        415.451,
        471.996,
        436.963,
        290.336,
        308.04
      ],
      "lat_p1_all": [
        52.4597,
        56.7313,
        73.7721,
        69.23,
        55.6639
      ],
      "probe_gain": 86.34464714250296
    },
    {
      "cell": "K16_N8",
      "wl": "fsdp",
      "nl": 64.78873239436619,
      "heaviest": [
        0,
        2
      ],
      "lat_mesh_median": 36.3399,
      "lat_p1_median": 35.5033,
      "lat_mesh_all": [
        36.2261,
        36.1849,
        36.4617,
        36.5017,
        36.3399
      ],
      "lat_p1_all": [
        35.3839,
        35.2892,
        35.6286,
        35.6591,
        35.5033
      ],
      "probe_gain": 2.3021527301946265
    },
    {
      "cell": "K16_N8",
      "wl": "hybrid_tp_pp",
      "nl": 65.75342465753425,
      "heaviest": [
        7,
        8
      ],
      "lat_mesh_median": 35.5009,
      "lat_p1_median": 34.2436,
      "lat_mesh_all": [
        35.5428,
        35.5111,
        35.3909,
        35.5009,
        35.2977
      ],
      "lat_p1_all": [
        34.5693,
        34.2436,
        33.7674,
        34.643,
        33.8273
      ],
      "probe_gain": 3.5416003537938496
    },
    {
      "cell": "K16_N8",
      "wl": "moe",
      "nl": 79.375,
      "heaviest": [
        0,
        6
      ],
      "lat_mesh_median": 392.812,
      "lat_p1_median": 269.342,
      "lat_mesh_all": [
        255.541,
        392.812,
        343.68,
        437.532,
        415.033
      ],
      "lat_p1_all": [
        301.066,
        269.342,
        283.976,
        245.816,
        220.61
      ],
      "probe_gain": 31.432339134242344
    },
    {
      "cell": "K16_N8",
      "wl": "ring_allreduce",
      "nl": 25.0,
      "heaviest": [
        0,
        15
      ],
      "lat_mesh_median": 35.4608,
      "lat_p1_median": 32.8486,
      "lat_mesh_all": [
        35.4608,
        35.5081,
        35.4415,
        35.5245,
        35.3188
      ],
      "lat_p1_all": [
        32.8339,
        32.9948,
        32.7935,
        32.8486,
        32.8619
      ],
      "probe_gain": 7.366444073455764
    },
    {
      "cell": "K16_N8",
      "wl": "tree_allreduce",
      "nl": 33.333333333333336,
      "heaviest": [
        0,
        2
      ],
      "lat_mesh_median": 29.4867,
      "lat_p1_median": 29.0754,
      "lat_mesh_all": [
        29.564,
        29.3836,
        29.5211,
        29.4754,
        29.4867
      ],
      "lat_p1_all": [
        29.1661,
        28.995,
        29.1073,
        29.0754,
        29.0656
      ],
      "probe_gain": 1.3948661599975605
    },
    {
      "cell": "K16_N8",
      "wl": "uniform_random",
      "nl": 79.08450363915355,
      "heaviest": [
        6,
        8
      ],
      "lat_mesh_median": 39.3226,
      "lat_p1_median": 39.7006,
      "lat_mesh_all": [
        39.3011,
        39.3226,
        39.3676,
        39.4125,
        39.2279
      ],
      "lat_p1_all": [
        40.1959,
        39.9574,
        39.6051,
        39.6892,
        39.7006
      ],
      "probe_gain": -0.9612792643416257
    },
    {
      "cell": "K32_N16",
      "wl": "ep_all_to_all",
      "nl": 91.53711886926517,
      "heaviest": [
        0,
        2
      ],
      "lat_mesh_median": 162.542,
      "lat_p1_median": 167.617,
      "lat_mesh_all": [
        137.206,
        163.007,
        162.542,
        133.72,
        167.741
      ],
      "lat_p1_all": [
        140.054,
        175.381,
        174.73,
        137.388,
        167.617
      ],
      "probe_gain": -3.1222699363856656
    },
    {
      "cell": "K32_N16",
      "wl": "fsdp",
      "nl": 75.52447552447552,
      "heaviest": [
        0,
        2
      ],
      "lat_mesh_median": 54.6977,
      "lat_p1_median": 55.8691,
      "lat_mesh_all": [
        54.6977,
        54.9896,
        54.4712,
        54.7522,
        54.5824
      ],
      "lat_p1_all": [
        56.0282,
        56.1956,
        55.635,
        55.8691,
        55.6944
      ],
      "probe_gain": -2.141589134460874
    },
    {
      "cell": "K32_N16",
      "wl": "hybrid_tp_pp",
      "nl": 76.51006711409396,
      "heaviest": [
        7,
        8
      ],
      "lat_mesh_median": 54.6977,
      "lat_p1_median": 267.759,
      "lat_mesh_all": [
        54.6977,
        54.9896,
        54.4712,
        54.7522,
        54.5824
      ],
      "lat_p1_all": [
        267.759,
        269.519,
        261.639,
        272.373,
        261.045
      ],
      "probe_gain": -389.5251537084741
    },
    {
      "cell": "K32_N16",
      "wl": "moe",
      "nl": 90.625,
      "heaviest": [
        0,
        6
      ],
      "lat_mesh_median": 166.76,
      "lat_p1_median": 548.78,
      "lat_mesh_all": [
        169.066,
        164.779,
        166.087,
        179.783,
        166.76
      ],
      "lat_p1_all": [
        559.791,
        551.434,
        548.78,
        512.55,
        545.82
      ],
      "probe_gain": -229.08371312065245
    },
    {
      "cell": "K32_N16",
      "wl": "ring_allreduce",
      "nl": 12.5,
      "heaviest": [
        0,
        31
      ],
      "lat_mesh_median": 38.5991,
      "lat_p1_median": 264.733,
      "lat_mesh_all": [
        38.6991,
        38.6944,
        38.5165,
        38.5709,
        38.5991
      ],
      "lat_p1_all": [
        292.76,
        228.416,
        230.451,
        264.733,
        279.105
      ],
      "probe_gain": -585.8527789508046
    },
    {
      "cell": "K32_N16",
      "wl": "tree_allreduce",
      "nl": 41.935483870967744,
      "heaviest": [
        0,
        2
      ],
      "lat_mesh_median": 39.0412,
      "lat_p1_median": 38.8954,
      "lat_mesh_all": [
        39.0742,
        39.0412,
        39.0345,
        39.1228,
        38.9301
      ],
      "lat_p1_all": [
        38.9256,
        38.8954,
        38.8919,
        38.9946,
        38.7944
      ],
      "probe_gain": 0.373451635707922
    },
    {
      "cell": "K32_N16",
      "wl": "uniform_random",
      "nl": 89.0562417094426,
      "heaviest": [
        5,
        18
      ],
      "lat_mesh_median": 162.162,
      "lat_p1_median": 363.528,
      "lat_mesh_all": [
        162.162,
        137.497,
        164.405,
        132.763,
        165.803
      ],
      "lat_p1_all": [
        356.777,
        369.449,
        357.944,
        363.528,
        382.097
      ],
      "probe_gain": -124.17582417582419
    },
    {
      "cell": "K32_N4",
      "wl": "ep_all_to_all",
      "nl": 91.53711886926517,
      "heaviest": [
        0,
        2
      ],
      "lat_mesh_median": 351.632,
      "lat_p1_median": 355.215,
      "lat_mesh_all": [
        375.338,
        341.481,
        349.797,
        353.086,
        351.632
      ],
      "lat_p1_all": [
        355.215,
        307.376,
        394.741,
        326.445,
        355.775
      ],
      "probe_gain": -1.0189630067798068
    },
    {
      "cell": "K32_N4",
      "wl": "fsdp",
      "nl": 75.52447552447552,
      "heaviest": [
        0,
        2
      ],
      "lat_mesh_median": 35.1342,
      "lat_p1_median": 34.9029,
      "lat_mesh_all": [
        35.062,
        35.1342,
        35.2498,
        35.2963,
        35.1053
      ],
      "lat_p1_all": [
        34.8422,
        34.9029,
        34.964,
        35.0723,
        34.8742
      ],
      "probe_gain": 0.658332906398886
    },
    {
      "cell": "K32_N4",
      "wl": "hybrid_tp_pp",
      "nl": 76.51006711409396,
      "heaviest": [
        7,
        8
      ],
      "lat_mesh_median": 35.7514,
      "lat_p1_median": 33.4873,
      "lat_mesh_all": [
        35.73,
        35.8283,
        35.7514,
        35.7135,
        35.8905
      ],
      "lat_p1_all": [
        33.4667,
        33.8615,
        33.4873,
        33.4606,
        34.1361
      ],
      "probe_gain": 6.332898851513505
    },
    {
      "cell": "K32_N4",
      "wl": "moe",
      "nl": 90.625,
      "heaviest": [
        0,
        6
      ],
      "lat_mesh_median": 346.302,
      "lat_p1_median": 344.335,
      "lat_mesh_all": [
        363.528,
        346.302,
        358.787,
        323.142,
        336.419
      ],
      "lat_p1_all": [
        356.963,
        344.13,
        345.313,
        342.218,
        344.335
      ],
      "probe_gain": 0.5680013398709916
    },
    {
      "cell": "K32_N4",
      "wl": "ring_allreduce",
      "nl": 12.5,
      "heaviest": [
        0,
        31
      ],
      "lat_mesh_median": 26.8458,
      "lat_p1_median": 23.1684,
      "lat_mesh_all": [
        26.648,
        26.7987,
        26.8458,
        26.854,
        26.9701
      ],
      "lat_p1_all": [
        23.0317,
        23.1684,
        23.2183,
        23.1095,
        23.2213
      ],
      "probe_gain": 13.698232125695649
    },
    {
      "cell": "K32_N4",
      "wl": "tree_allreduce",
      "nl": 41.935483870967744,
      "heaviest": [
        0,
        2
      ],
      "lat_mesh_median": 24.9715,
      "lat_p1_median": 24.8492,
      "lat_mesh_all": [
        24.987,
        24.8869,
        25.0075,
        24.9715,
        24.9604
      ],
      "lat_p1_all": [
        24.8492,
        24.7585,
        24.8781,
        24.8617,
        24.8484
      ],
      "probe_gain": 0.4897583244899153
    },
    {
      "cell": "K32_N4",
      "wl": "uniform_random",
      "nl": 89.0562417094426,
      "heaviest": [
        5,
        18
      ],
      "lat_mesh_median": 40.4578,
      "lat_p1_median": 42.0715,
      "lat_mesh_all": [
        40.4578,
        40.2758,
        40.6503,
        40.3386,
        40.6812
      ],
      "lat_p1_all": [
        42.1267,
        41.3432,
        41.5936,
        42.0715,
        42.2396
      ],
      "probe_gain": -3.988600467647775
    },
    {
      "cell": "K32_N8",
      "wl": "ep_all_to_all",
      "nl": 91.53711886926517,
      "heaviest": [
        0,
        2
      ],
      "lat_mesh_median": 238.791,
      "lat_p1_median": 242.826,
      "lat_mesh_all": [
        254.219,
        234.066,
        243.018,
        228.327,
        238.791
      ],
      "lat_p1_all": [
        251.679,
        226.7,
        242.826,
        246.898,
        234.101
      ],
      "probe_gain": -1.6897621769664672
    },
    {
      "cell": "K32_N8",
      "wl": "fsdp",
      "nl": 75.52447552447552,
      "heaviest": [
        0,
        2
      ],
      "lat_mesh_median": 55.385,
      "lat_p1_median": 56.3899,
      "lat_mesh_all": [
        55.3448,
        55.3524,
        55.385,
        55.4751,
        55.649
      ],
      "lat_p1_all": [
        55.7806,
        56.3899,
        56.1261,
        56.4616,
        56.5915
      ],
      "probe_gain": -1.8143901778459859
    },
    {
      "cell": "K32_N8",
      "wl": "hybrid_tp_pp",
      "nl": 76.51006711409396,
      "heaviest": [
        7,
        8
      ],
      "lat_mesh_median": 54.511,
      "lat_p1_median": 342.176,
      "lat_mesh_all": [
        54.2219,
        54.6495,
        54.4258,
        54.511,
        54.6416
      ],
      "lat_p1_all": [
        334.101,
        345.205,
        351.957,
        342.176,
        339.69
      ],
      "probe_gain": -527.7191759461392
    },
    {
      "cell": "K32_N8",
      "wl": "moe",
      "nl": 90.625,
      "heaviest": [
        0,
        6
      ],
      "lat_mesh_median": 297.862,
      "lat_p1_median": 517.073,
      "lat_mesh_all": [
        297.862,
        289.852,
        298.486,
        301.214,
        294.436
      ],
      "lat_p1_all": [
        473.957,
        486.048,
        546.899,
        517.073,
        536.643
      ],
      "probe_gain": -73.59481907729081
    },
    {
      "cell": "K32_N8",
      "wl": "ring_allreduce",
      "nl": 12.5,
      "heaviest": [
        0,
        31
      ],
      "lat_mesh_median": 37.7481,
      "lat_p1_median": 30.1121,
      "lat_mesh_all": [
        37.6688,
        37.7481,
        38.0018,
        37.7428,
        37.9348
      ],
      "lat_p1_all": [
        30.0558,
        30.1121,
        30.2061,
        30.0157,
        30.2336
      ],
      "probe_gain": 20.22883270946087
    },
    {
      "cell": "K32_N8",
      "wl": "tree_allreduce",
      "nl": 41.935483870967744,
      "heaviest": [
        0,
        2
      ],
      "lat_mesh_median": 32.201,
      "lat_p1_median": 31.9611,
      "lat_mesh_all": [
        32.1648,
        32.208,
        32.201,
        32.2175,
        32.1191
      ],
      "lat_p1_all": [
        31.9093,
        31.9711,
        31.9611,
        31.9845,
        31.876
      ],
      "probe_gain": 0.7450079190087333
    },
    {
      "cell": "K32_N8",
      "wl": "uniform_random",
      "nl": 89.0562417094426,
      "heaviest": [
        5,
        18
      ],
      "lat_mesh_median": 61.0792,
      "lat_p1_median": 518.201,
      "lat_mesh_all": [
        61.0792,
        61.1294,
        60.5221,
        61.0632,
        61.2854
      ],
      "lat_p1_all": [
        491.697,
        559.878,
        530.998,
        518.201,
        516.773
      ],
      "probe_gain": -748.408296113898
    },
    {
      "cell": "K4_N16",
      "wl": "ep_all_to_all",
      "nl": 33.333333333333336,
      "heaviest": [
        0,
        3
      ],
      "lat_mesh_median": 30.7143,
      "lat_p1_median": 29.3575,
      "lat_mesh_all": [
        30.8156,
        30.6265,
        30.8871,
        30.4881,
        30.7143
      ],
      "lat_p1_all": [
        29.4828,
        29.236,
        29.4338,
        29.1693,
        29.3575
      ],
      "probe_gain": 4.4174863174482235
    },
    {
      "cell": "K4_N16",
      "wl": "fsdp",
      "nl": 33.333333333333336,
      "heaviest": [
        0,
        3
      ],
      "lat_mesh_median": 29.708,
      "lat_p1_median": 28.6682,
      "lat_mesh_all": [
        29.6602,
        29.6802,
        29.708,
        29.7507,
        29.7851
      ],
      "lat_p1_all": [
        28.6221,
        28.6514,
        28.6682,
        28.7554,
        28.8064
      ],
      "probe_gain": 3.500067321933485
    },
    {
      "cell": "K4_N16",
      "wl": "hybrid_tp_pp",
      "nl": 33.333333333333336,
      "heaviest": [
        0,
        3
      ],
      "lat_mesh_median": 29.708,
      "lat_p1_median": 28.6682,
      "lat_mesh_all": [
        29.6602,
        29.6802,
        29.708,
        29.7507,
        29.7851
      ],
      "lat_p1_all": [
        28.6221,
        28.6514,
        28.6682,
        28.7554,
        28.8064
      ],
      "probe_gain": 3.500067321933485
    },
    {
      "cell": "K4_N16",
      "wl": "moe",
      "nl": 35.0,
      "heaviest": [
        0,
        3
      ],
      "lat_mesh_median": 31.1205,
      "lat_p1_median": 29.8205,
      "lat_mesh_all": [
        31.0293,
        31.1205,
        31.2562,
        31.335,
        31.077
      ],
      "lat_p1_all": [
        29.7926,
        29.8205,
        29.9218,
        29.9516,
        29.7926
      ],
      "probe_gain": 4.177310775855146
    },
    {
      "cell": "K4_N16",
      "wl": "ring_allreduce",
      "nl": 50.0,
      "heaviest": [
        0,
        3
      ],
      "lat_mesh_median": 31.8859,
      "lat_p1_median": 30.435,
      "lat_mesh_all": [
        32.0186,
        31.7375,
        31.8859,
        31.835,
        32.0264
      ],
      "lat_p1_all": [
        30.5232,
        30.312,
        30.435,
        30.3071,
        30.4806
      ],
      "probe_gain": 4.550287117503351
    },
    {
      "cell": "K4_N16",
      "wl": "tree_allreduce",
      "nl": 0.0,
      "heaviest": [
        0,
        3
      ],
      "lat_mesh_median": 26.5026,
      "lat_p1_median": 26.2371,
      "lat_mesh_all": [
        26.5026,
        26.4609,
        26.5407,
        26.4309,
        26.5285
      ],
      "lat_p1_all": [
        26.2399,
        26.1999,
        26.2371,
        26.1394,
        26.2716
      ],
      "probe_gain": 1.0017885037694392
    },
    {
      "cell": "K4_N16",
      "wl": "uniform_random",
      "nl": 31.995712199759712,
      "heaviest": [
        0,
        3
      ],
      "lat_mesh_median": 29.708,
      "lat_p1_median": 28.6682,
      "lat_mesh_all": [
        29.6602,
        29.6802,
        29.708,
        29.7507,
        29.7851
      ],
      "lat_p1_all": [
        28.6221,
        28.6514,
        28.6682,
        28.7554,
        28.8064
      ],
      "probe_gain": 3.500067321933485
    },
    {
      "cell": "K4_N4",
      "wl": "ep_all_to_all",
      "nl": 33.333333333333336,
      "heaviest": [
        0,
        3
      ],
      "lat_mesh_median": 22.4376,
      "lat_p1_median": 21.6145,
      "lat_mesh_all": [
        22.4376,
        22.3232,
        22.3256,
        22.5689,
        22.5911
      ],
      "lat_p1_all": [
        21.6507,
        21.5825,
        21.4966,
        21.6145,
        21.6416
      ],
      "probe_gain": 3.668395906870611
    },
    {
      "cell": "K4_N4",
      "wl": "fsdp",
      "nl": 33.333333333333336,
      "heaviest": [
        0,
        3
      ],
      "lat_mesh_median": 22.2948,
      "lat_p1_median": 21.6378,
      "lat_mesh_all": [
        22.1912,
        22.233,
        22.3832,
        22.2948,
        22.3269
      ],
      "lat_p1_all": [
        21.6135,
        21.6378,
        21.7643,
        21.6716,
        21.6298
      ],
      "probe_gain": 2.9468755046019703
    },
    {
      "cell": "K4_N4",
      "wl": "hybrid_tp_pp",
      "nl": 33.333333333333336,
      "heaviest": [
        0,
        3
      ],
      "lat_mesh_median": 22.0932,
      "lat_p1_median": 21.4766,
      "lat_mesh_all": [
        22.0603,
        22.0932,
        22.0834,
        22.1387,
        22.2283
      ],
      "lat_p1_all": [
        21.5385,
        21.4147,
        21.454,
        21.4766,
        21.5983
      ],
      "probe_gain": 2.7909039885575573
    },
    {
      "cell": "K4_N4",
      "wl": "moe",
      "nl": 35.0,
      "heaviest": [
        0,
        3
      ],
      "lat_mesh_median": 22.5203,
      "lat_p1_median": 21.7797,
      "lat_mesh_all": [
        22.5203,
        22.5192,
        22.5337,
        22.2831,
        22.5711
      ],
      "lat_p1_all": [
        21.8979,
        21.7797,
        21.711,
        21.5467,
        21.8459
      ],
      "probe_gain": 3.2885885179149508
    },
    {
      "cell": "K4_N4",
      "wl": "ring_allreduce",
      "nl": 50.0,
      "heaviest": [
        0,
        3
      ],
      "lat_mesh_median": 23.3161,
      "lat_p1_median": 22.2527,
      "lat_mesh_all": [
        23.3161,
        23.3254,
        23.2224,
        23.1909,
        23.3319
      ],
      "lat_p1_all": [
        22.2392,
        22.2824,
        22.2527,
        22.2112,
        22.3444
      ],
      "probe_gain": 4.560797045818117
    },
    {
      "cell": "K4_N4",
      "wl": "tree_allreduce",
      "nl": 0.0,
      "heaviest": [
        0,
        3
      ],
      "lat_mesh_median": 20.5028,
      "lat_p1_median": 20.5066,
      "lat_mesh_all": [
        20.5247,
        20.5124,
        20.384,
        20.4062,
        20.5028
      ],
      "lat_p1_all": [
        20.5369,
        20.5133,
        20.3908,
        20.4128,
        20.5066
      ],
      "probe_gain": -0.01853405388531444
    },
    {
      "cell": "K4_N4",
      "wl": "uniform_random",
      "nl": 31.995712199759712,
      "heaviest": [
        0,
        3
      ],
      "lat_mesh_median": 21.7527,
      "lat_p1_median": 21.0808,
      "lat_mesh_all": [
        21.6483,
        21.7978,
        21.6484,
        21.7917,
        21.7527
      ],
      "lat_p1_all": [
        21.0105,
        21.0365,
        21.1325,
        21.128,
        21.0808
      ],
      "probe_gain": 3.0888119635723417
    },
    {
      "cell": "K4_N8",
      "wl": "ep_all_to_all",
      "nl": 33.333333333333336,
      "heaviest": [
        0,
        3
      ],
      "lat_mesh_median": 27.5312,
      "lat_p1_median": 26.6719,
      "lat_mesh_all": [
        27.5169,
        27.5312,
        27.6062,
        27.4755,
        27.5637
      ],
      "lat_p1_all": [
        26.6128,
        26.5614,
        26.6719,
        26.7736,
        26.7063
      ],
      "probe_gain": 3.1211861451734673
    },
    {
      "cell": "K4_N8",
      "wl": "fsdp",
      "nl": 33.333333333333336,
      "heaviest": [
        0,
        3
      ],
      "lat_mesh_median": 26.805,
      "lat_p1_median": 26.1358,
      "lat_mesh_all": [
        26.6185,
        26.8182,
        26.4677,
        26.8418,
        26.805
      ],
      "lat_p1_all": [
        25.9847,
        26.1358,
        25.8918,
        26.2552,
        26.2265
      ],
      "probe_gain": 2.4965491512777467
    },
    {
      "cell": "K4_N8",
      "wl": "hybrid_tp_pp",
      "nl": 33.333333333333336,
      "heaviest": [
        0,
        3
      ],
      "lat_mesh_median": 25.5419,
      "lat_p1_median": 25.0244,
      "lat_mesh_all": [
        25.5368,
        25.4515,
        25.6423,
        25.5419,
        25.5535
      ],
      "lat_p1_all": [
        25.0567,
        24.9882,
        25.1727,
        24.962,
        25.0244
      ],
      "probe_gain": 2.0260826328503296
    },
    {
      "cell": "K4_N8",
      "wl": "moe",
      "nl": 35.0,
      "heaviest": [
        0,
        3
      ],
      "lat_mesh_median": 27.4188,
      "lat_p1_median": 26.6447,
      "lat_mesh_all": [
        27.377,
        27.4188,
        27.3239,
        27.4835,
        27.7308
      ],
      "lat_p1_all": [
        26.7131,
        26.6447,
        26.5947,
        26.6406,
        26.908
      ],
      "probe_gain": 2.823245364494437
    },
    {
      "cell": "K4_N8",
      "wl": "ring_allreduce",
      "nl": 50.0,
      "heaviest": [
        0,
        3
      ],
      "lat_mesh_median": 29.686,
      "lat_p1_median": 28.6914,
      "lat_mesh_all": [
        29.686,
        29.6925,
        29.4922,
        29.4606,
        29.7681
      ],
      "lat_p1_all": [
        28.7638,
        28.6914,
        28.4871,
        28.6026,
        28.8295
      ],
      "probe_gain": 3.350400862359356
    },
    {
      "cell": "K4_N8",
      "wl": "tree_allreduce",
      "nl": 0.0,
      "heaviest": [
        0,
        3
      ],
      "lat_mesh_median": 25.1937,
      "lat_p1_median": 25.1924,
      "lat_mesh_all": [
        25.1937,
        25.107,
        25.1031,
        25.2142,
        25.3043
      ],
      "lat_p1_all": [
        25.1924,
        25.1072,
        25.1063,
        25.2138,
        25.3056
      ],
      "probe_gain": 0.005160020163773178
    },
    {
      "cell": "K4_N8",
      "wl": "uniform_random",
      "nl": 31.995712199759712,
      "heaviest": [
        0,
        3
      ],
      "lat_mesh_median": 25.5419,
      "lat_p1_median": 25.0244,
      "lat_mesh_all": [
        25.5368,
        25.4515,
        25.6423,
        25.5419,
        25.5535
      ],
      "lat_p1_all": [
        25.0567,
        24.9882,
        25.1727,
        24.962,
        25.0244
      ],
      "probe_gain": 2.0260826328503296
    },
    {
      "cell": "K8_N16",
      "wl": "ep_all_to_all",
      "nl": 66.47526212349409,
      "heaviest": [
        0,
        2
      ],
      "lat_mesh_median": 41.019,
      "lat_p1_median": 40.0822,
      "lat_mesh_all": [
        40.7525,
        40.7957,
        41.2292,
        41.0757,
        41.019
      ],
      "lat_p1_all": [
        39.7157,
        39.8397,
        40.0822,
        40.1023,
        40.1315
      ],
      "probe_gain": 2.2838196933128505
    },
    {
      "cell": "K8_N16",
      "wl": "fsdp",
      "nl": 64.28571428571429,
      "heaviest": [
        0,
        2
      ],
      "lat_mesh_median": 39.1033,
      "lat_p1_median": 38.4161,
      "lat_mesh_all": [
        39.1894,
        39.2496,
        39.1033,
        38.8683,
        39.0305
      ],
      "lat_p1_all": [
        38.5735,
        38.5102,
        38.4161,
        38.2081,
        38.1383
      ],
      "probe_gain": 1.757396434572011
    },
    {
      "cell": "K8_N16",
      "wl": "hybrid_tp_pp",
      "nl": 64.28571428571429,
      "heaviest": [
        0,
        2
      ],
      "lat_mesh_median": 39.1033,
      "lat_p1_median": 38.4161,
      "lat_mesh_all": [
        39.1894,
        39.2496,
        39.1033,
        38.8683,
        39.0305
      ],
      "lat_p1_all": [
        38.5735,
        38.5102,
        38.4161,
        38.1383,
        38.2081
      ],
      "probe_gain": 1.757396434572011
    },
    {
      "cell": "K8_N16",
      "wl": "moe",
      "nl": 65.0,
      "heaviest": [
        0,
        3
      ],
      "lat_mesh_median": 39.5595,
      "lat_p1_median": 37.2449,
      "lat_mesh_all": [
        39.5246,
        39.4955,
        39.6153,
        39.5595,
        39.627
      ],
      "lat_p1_all": [
        37.2952,
        37.0742,
        37.3957,
        37.2449,
        37.2445
      ],
      "probe_gain": 5.850933404112789
    },
    {
      "cell": "K8_N16",
      "wl": "ring_allreduce",
      "nl": 25.0,
      "heaviest": [
        0,
        7
      ],
      "lat_mesh_median": 36.284,
      "lat_p1_median": 32.5037,
      "lat_mesh_all": [
        36.0852,
        36.3408,
        36.284,
        36.13,
        36.5276
      ],
      "lat_p1_all": [
        32.299,
        32.592,
        32.5037,
        32.347,
        32.6651
      ],
      "probe_gain": 10.418641825598051
    },
    {
      "cell": "K8_N16",
      "wl": "tree_allreduce",
      "nl": 28.571428571428573,
      "heaviest": [
        0,
        2
      ],
      "lat_mesh_median": 30.5835,
      "lat_p1_median": 30.0913,
      "lat_mesh_all": [
        30.5597,
        30.484,
        30.6756,
        30.5835,
        30.7445
      ],
      "lat_p1_all": [
        30.0528,
        29.9642,
        30.0987,
        30.2347,
        30.0913
      ],
      "probe_gain": 1.6093645266238343
    },
    {
      "cell": "K8_N16",
      "wl": "uniform_random",
      "nl": 66.89978246215792,
      "heaviest": [
        1,
        4
      ],
      "lat_mesh_median": 39.1033,
      "lat_p1_median": 38.4666,
      "lat_mesh_all": [
        39.1894,
        39.2496,
        39.1033,
        38.8683,
        39.0305
      ],
      "lat_p1_all": [
        38.575,
        38.4961,
        38.4666,
        38.0982,
        38.3097
      ],
      "probe_gain": 1.6282513240570429
    },
    {
      "cell": "K8_N4",
      "wl": "ep_all_to_all",
      "nl": 66.47526212349409,
      "heaviest": [
        0,
        2
      ],
      "lat_mesh_median": 27.93,
      "lat_p1_median": 26.3739,
      "lat_mesh_all": [
        27.93,
        28.0393,
        27.8661,
        28.1397,
        27.8541
      ],
      "lat_p1_all": [
        26.2281,
        26.5651,
        26.3739,
        26.5902,
        26.3403
      ],
      "probe_gain": 5.571428571428574
    },
    {
      "cell": "K8_N4",
      "wl": "fsdp",
      "nl": 64.28571428571429,
      "heaviest": [
        0,
        2
      ],
      "lat_mesh_median": 26.8142,
      "lat_p1_median": 25.9344,
      "lat_mesh_all": [
        26.7882,
        26.9744,
        26.8142,
        27.0483,
        26.7431
      ],
      "lat_p1_all": [
        25.9088,
        25.9998,
        25.9344,
        26.101,
        25.7904
      ],
      "probe_gain": 3.2810973290271552
    },
    {
      "cell": "K8_N4",
      "wl": "hybrid_tp_pp",
      "nl": 64.28571428571429,
      "heaviest": [
        0,
        2
      ],
      "lat_mesh_median": 26.6295,
      "lat_p1_median": 25.7437,
      "lat_mesh_all": [
        26.3902,
        26.6004,
        26.6295,
        26.8431,
        26.7623
      ],
      "lat_p1_all": [
        25.5506,
        25.7437,
        25.6942,
        25.9626,
        25.949
      ],
      "probe_gain": 3.3263861506975334
    },
    {
      "cell": "K8_N4",
      "wl": "moe",
      "nl": 65.0,
      "heaviest": [
        0,
        3
      ],
      "lat_mesh_median": 27.485,
      "lat_p1_median": 25.008,
      "lat_mesh_all": [
        27.3855,
        27.3931,
        27.485,
        27.607,
        27.548
      ],
      "lat_p1_all": [
        25.0008,
        25.008,
        24.9956,
        25.1897,
        25.2017
      ],
      "probe_gain": 9.012188466436239
    },
    {
      "cell": "K8_N4",
      "wl": "ring_allreduce",
      "nl": 25.0,
      "heaviest": [
        0,
        7
      ],
      "lat_mesh_median": 25.3035,
      "lat_p1_median": 22.2956,
      "lat_mesh_all": [
        25.2816,
        25.3267,
        25.3035,
        25.1416,
        25.312
      ],
      "lat_p1_all": [
        22.327,
        22.2724,
        22.3499,
        22.1773,
        22.2956
      ],
      "probe_gain": 11.887288319797655
    },
    {
      "cell": "K8_N4",
      "wl": "tree_allreduce",
      "nl": 28.571428571428573,
      "heaviest": [
        0,
        2
      ],
      "lat_mesh_median": 22.4564,
      "lat_p1_median": 22.121,
      "lat_mesh_all": [
        22.4564,
        22.4286,
        22.4433,
        22.5175,
        22.5029
      ],
      "lat_p1_all": [
        22.1265,
        22.0538,
        22.0744,
        22.121,
        22.1538
      ],
      "probe_gain": 1.4935608557026057
    },
    {
      "cell": "K8_N4",
      "wl": "uniform_random",
      "nl": 66.89978246215792,
      "heaviest": [
        1,
        4
      ],
      "lat_mesh_median": 26.5896,
      "lat_p1_median": 26.0447,
      "lat_mesh_all": [
        26.675,
        26.5145,
        26.5896,
        26.5751,
        26.6041
      ],
      "lat_p1_all": [
        25.979,
        26.1234,
        26.0447,
        26.0443,
        26.0691
      ],
      "probe_gain": 2.049297469687404
    },
    {
      "cell": "K8_N8",
      "wl": "ep_all_to_all",
      "nl": 66.47526212349409,
      "heaviest": [
        0,
        2
      ],
      "lat_mesh_median": 40.9466,
      "lat_p1_median": 37.2457,
      "lat_mesh_all": [
        41.8285,
        40.4986,
        40.9466,
        40.5346,
        41.7599
      ],
      "lat_p1_all": [
        37.8895,
        36.8316,
        37.2457,
        36.7945,
        38.1636
      ],
      "probe_gain": 9.038357275085104
    },
    {
      "cell": "K8_N8",
      "wl": "fsdp",
      "nl": 64.28571428571429,
      "heaviest": [
        0,
        2
      ],
      "lat_mesh_median": 36.2433,
      "lat_p1_median": 34.3254,
      "lat_mesh_all": [
        36.1007,
        35.956,
        36.319,
        36.2433,
        36.2518
      ],
      "lat_p1_all": [
        34.2121,
        34.2687,
        34.4837,
        34.3627,
        34.3254
      ],
      "probe_gain": 5.291736679606979
    },
    {
      "cell": "K8_N8",
      "wl": "hybrid_tp_pp",
      "nl": 64.28571428571429,
      "heaviest": [
        0,
        2
      ],
      "lat_mesh_median": 34.7161,
      "lat_p1_median": 32.9585,
      "lat_mesh_all": [
        34.8658,
        34.7161,
        34.5941,
        34.6683,
        34.8611
      ],
      "lat_p1_all": [
        32.9876,
        32.9585,
        32.8611,
        32.811,
        33.2215
      ],
      "probe_gain": 5.062780669487634
    },
    {
      "cell": "K8_N8",
      "wl": "moe",
      "nl": 65.0,
      "heaviest": [
        0,
        3
      ],
      "lat_mesh_median": 38.7012,
      "lat_p1_median": 32.818,
      "lat_mesh_all": [
        38.5224,
        38.3371,
        38.7012,
        39.0094,
        38.8971
      ],
      "lat_p1_all": [
        32.7095,
        32.5796,
        32.843,
        32.818,
        32.9786
      ],
      "probe_gain": 15.201595816150407
    },
    {
      "cell": "K8_N8",
      "wl": "ring_allreduce",
      "nl": 25.0,
      "heaviest": [
        0,
        7
      ],
      "lat_mesh_median": 34.8114,
      "lat_p1_median": 28.7659,
      "lat_mesh_all": [
        34.8114,
        34.6726,
        34.8446,
        34.6062,
        34.9819
      ],
      "lat_p1_all": [
        28.7659,
        28.7077,
        28.9606,
        28.7504,
        28.9884
      ],
      "probe_gain": 17.36643743141615
    },
    {
      "cell": "K8_N8",
      "wl": "tree_allreduce",
      "nl": 28.571428571428573,
      "heaviest": [
        0,
        2
      ],
      "lat_mesh_median": 29.5469,
      "lat_p1_median": 28.7322,
      "lat_mesh_all": [
        29.5387,
        29.4998,
        29.6194,
        29.5469,
        29.6117
      ],
      "lat_p1_all": [
        28.6893,
        28.5237,
        28.7346,
        28.7322,
        28.7639
      ],
      "probe_gain": 2.7573112576953993
    },
    {
      "cell": "K8_N8",
      "wl": "uniform_random",
      "nl": 66.89978246215792,
      "heaviest": [
        1,
        4
      ],
      "lat_mesh_median": 34.7161,
      "lat_p1_median": 34.4013,
      "lat_mesh_all": [
        34.8658,
        34.7161,
        34.6683,
        34.5941,
        34.8611
      ],
      "lat_p1_all": [
        34.597,
        34.4013,
        34.3951,
        34.2952,
        34.6091
      ],
      "probe_gain": 0.9067838841344454
    }
  ],
  "rho_nl_vs_probe": -0.31788830484122094,
  "wall_s": 4466.358595132828
}